papolarity/__init__.py
papolarity/__main__.py
papolarity/annotation.py
papolarity/annotation_filter.py
papolarity/cli.py
papolarity/clipping.py
papolarity/coreutils_sort.py
papolarity/coverage_profile.py
papolarity/fasta_reader.py
papolarity/gtf_parser.py
papolarity/gzip_utils.py
papolarity/nullcontext.py
papolarity/polarity_score.py
papolarity/profile_comparison.py
papolarity/segmentation.py
papolarity/tsv_reader.py
papolarity/utils.py
papolarity/version.py
papolarity/bin/__init__.py
papolarity/bin/adjust_features.py
papolarity/bin/cds_annotation.py
papolarity/bin/cds_sequence.py
papolarity/bin/choose_best.py
papolarity/bin/clip_cds.py
papolarity/bin/compare_coverage.py
papolarity/bin/coverage_features.py
papolarity/bin/flatten_coverage.py
papolarity/bin/get_coverage.py
papolarity/bin/plot_distribution.py
papolarity/bin/pool_coverage.py
papolarity/dto/__init__.py
papolarity/dto/coding_transcript_info.py
papolarity/dto/coverage_interval.py
papolarity/dto/dataclass_tsv_serializable.py
papolarity/dto/interval.py
papolarity/dto/transcript_coverage.py
papolarity-1.1.2.dist-info/METADATA
papolarity-1.1.2.dist-info/WHEEL
papolarity-1.1.2.dist-info/entry_points.txt
papolarity-1.1.2.dist-info/top_level.txt
papolarity-1.1.2.dist-info/RECORD
