Metadata-Version: 2.1
Name: papolarity
Version: 1.1.2
Summary: Papolarity is a tool to analyze polarity of transcriptomic alignments such as Ribo-seq and RNA-seq.
Home-page: https://github.com/autosome-ru/papolarity
Author: Ilya Vorontsov
Author-email: vorontsov.i.e@gmail.com
License: Papolarity is licensed under WTFPL, but if you prefer more standard licenses, feel free to treat it as MIT license
Keywords: bioinformatics NGS coverage alignment polarity Ribo-seq RNA-seq
Platform: UNKNOWN
Classifier: Topic :: Scientific/Engineering :: Bio-Informatics
Classifier: Intended Audience :: Science/Research
Classifier: License :: OSI Approved :: MIT License
Classifier: Development Status :: 5 - Production/Stable
Classifier: Operating System :: OS Independent
Classifier: Programming Language :: Python :: 3.7
Classifier: Programming Language :: Python :: 3.8
Requires-Python: >=3.7
Requires-Dist: pybedtools (>=0.8.0)
Requires-Dist: numpy (>=1.8.0)
Requires-Dist: sklearn
Requires-Dist: six
Requires-Dist: matplotlib
Requires-Dist: seaborn
Provides-Extra: dev
Requires-Dist: pytest ; extra == 'dev'
Requires-Dist: pytest-benchmark ; extra == 'dev'
Requires-Dist: flake8 ; extra == 'dev'
Requires-Dist: tox ; extra == 'dev'
Requires-Dist: wheel ; extra == 'dev'
Requires-Dist: twine ; extra == 'dev'
Requires-Dist: setuptools-scm ; extra == 'dev'
